{"chunks":[{"text":"- Marchés financiers\\n- – Résultat net de 308 M$ au premier trimestre de 2024 contre 298 M$ au trimestre correspondant de 2023, une hausse de 3 %.\\n- – Revenu total en équivalent imposable de 755 M$, une augmentation de 66 M$ ou 10 % attribuable à la hausse des revenus des marchés mondiaux ainsi qu’à la hausse des revenus provenant des services financiers aux entreprises et services de banque d’investissement.\\n- – Les frais autres que d’intérêts se chiffrent à 313 M$ au premier trimestre de 2024, par rapport à 287 M$ au trimestre correspondant de 2023, une hausse en partie attribuable à la rémunération et aux avantages du personnel ainsi qu’aux investissements technologiques du secteur.\\n- – Des dotations aux pertes de crédit de 17 M$ ont été enregistrées au premier trimestre de 2024, comparativement à des récupérations de pertes de crédit de 9 M$ au trimestre correspondant de 2023.\\n- – Le ratio d’efficience(1) en équivalent imposable de 41,5 % s’améliore comparativement à 41,7 % au premier trimestre de 2023.","grounding":[{"box":{"l":0.052153974771499634,"t":0.4062640070915222,"r":0.9424724578857422,"b":0.5329976677894592},"page":1}],"chunk_type":"text","chunk_id":"72fd82cc-88bb-47db-85f3-e0ea02412d27"},{"text":"- Financement spécialisé aux États-Unis et International\\n- Résultat net de 150 M$ au premier trimestre de 2024 contre 147 M$ au trimestre correspondant de 2023.\\n- Revenu total de 326 M$ au premier trimestre de 2024, en hausse de 2 % par rapport au premier trimestre de 2023, une augmentation essentiellement attribuable à la croissance des revenus de la filiale ABA Bank.\\n- Les frais autres que d’intérêts de 100 M$ au premier trimestre de 2024 sont en hausse de 2 % par rapport au trimestre correspondant de 2023, une hausse principalement attribuable à la croissance des activités de la filiale ABA Bank.\\n- Les dotations aux pertes de crédit sont en hausse de 1 M$ par rapport au premier trimestre de 2023.\\n- Le ratio d’efficience(1) de 30,7 % est stable par rapport au trimestre correspondant de 2023.","grounding":[{"box":{"l":0.05239996314048767,"t":0.5407056212425232,"r":0.9270305633544922,"b":0.6559378504753113},"page":1}],"chunk_type":"text","chunk_id":"0684b5d5-076f-4026-a69b-526dd1a8886f"},{"text":"- **Autres**\\n  - Perte nette de 71 M$ au premier trimestre de 2024, contre une perte nette de 93 M$ au trimestre correspondant de 2023, une variation qui s’explique par la charge d’impôts de 24 M$ liée aux mesures fiscales 2022 du gouvernement du Canada enregistrée au premier trimestre de 2023.","grounding":[{"box":{"l":0.05326598882675171,"t":0.6631566882133484,"r":0.9421742558479309,"b":0.7147707343101501},"page":1}],"chunk_type":"text","chunk_id":"5d9424ca-34ab-43f6-9394-787f5bc0a9ec"},{"text":"- Gestion du capital\\n- Ratio des fonds propres de catégorie 1 sous forme d’actions ordinaires (CET1) selon Bâle III (2) de 13,1 % au 31 janvier 2024, en baisse par rapport à 13,5 % au 31 octobre 2023, notamment en raison de l’incidence négative de la mise en œuvre des cadres révisés relativement au risque de marché et au risque lié à l’ajustement de l’évaluation de crédit (CVA).\\n- Ratio de levier selon Bâle III (2) de 4,3 % au 31 janvier 2024, en baisse par rapport à 4,4 % au 31 octobre 2023.","grounding":[{"box":{"l":0.053262919187545776,"t":0.7208923697471619,"r":0.9361549615859985,"b":0.7969904541969299},"page":1}],"chunk_type":"text","chunk_id":"3760fa4c-d3fb-4d88-b140-c15366f82803"},{"text":"(1)  Consulter le « Glossaire » aux pages 43 à 46 pour plus de détails sur la composition de ces mesures.\\n(2)  Consulter le « Mode de présentation de l’information » aux pages 4 à 8 pour de plus amples renseignements sur les mesures de gestion du capital.","grounding":[{"box":{"l":0.05510967969894409,"t":0.8325279355049133,"r":0.7442837953567505,"b":0.8568897843360901},"page":1}],"chunk_type":"text","chunk_id":"2cc0fd86-91dc-4a50-9a35-19fd4b0c4031"},{"text":"Banque Nationale du Canada   \\nRapport aux actionnaires, premier trimestre de 2024","grounding":[{"box":{"l":0.6524089574813843,"t":0.9393221735954285,"r":0.8935798406600952,"b":0.9606431126594543},"page":2}],"chunk_type":"marginalia","chunk_id":"66fdca68-4f8f-4252-b1e9-9642a56f627d"},{"text":"2","grounding":[{"box":{"l":0.9290042519569397,"t":0.9428251385688782,"r":0.9450158476829529,"b":0.9573262333869934},"page":2}],"chunk_type":"marginalia","chunk_id":"55b611dd-f422-42be-bc26-db426bcb2ee5"},{"text":"# Rapport\\nde gestion\\nDaté du 27 février 2024","grounding":[{"box":{"l":0.5785637497901917,"t":0.07540396600961685,"r":0.9495689272880554,"b":0.22214195132255554},"page":2}],"chunk_type":"text","chunk_id":"36ab21c3-bd26-4554-a301-15fac84d944a"}]}
